.cvsignore
README.txt
setup.py
src/.cvsignore
src/ifrit/CHANGES.txt
src/ifrit/COPYRIGHT.txt
src/ifrit/LICENSE.txt
src/ifrit/README.txt
src/ifrit/__init__.py
src/ifrit/adapters.py
src/ifrit/elementtree.zcml
src/ifrit/interfaces.py
src/ifrit/lxml_utils.py
src/ifrit/lxml_utils.zcml
src/ifrit/meta.zcml
src/ifrit/nodes_with_markers.txt
src/ifrit/objectify_utils.py
src/ifrit/objectify_utils.zcml
src/ifrit/version.txt
src/ifrit/zcml.py
src/ifrit.egg-info/PKG-INFO
src/ifrit.egg-info/SOURCES.txt
src/ifrit.egg-info/dependency_links.txt
src/ifrit.egg-info/not-zip-safe
src/ifrit.egg-info/requires.txt
src/ifrit.egg-info/top_level.txt
src/ifrit/tests/__init__.py
src/ifrit/tests/test_adapters.py
