Metadata-Version: 1.0
Name: ifrit
Version: 0.3.1
Summary: XPath / ElementTree path adapters
Home-page: http://agendaless.com/Members/tseaver/software/ifrit
Author: Tres Seaver, Agendaless Consulting, Inc.
Author-email: tseaver@agendaless.com
License: ZPL 2.1
Platform: UNKNOWN
